onecache/__init__.py
onecache/cache_value.py
onecache/utils.py
onecache-0.8.0.dist-info/METADATA
onecache-0.8.0.dist-info/WHEEL
onecache-0.8.0.dist-info/RECORD
